LICENSE
README.md
setup.py
random_regex/__init__.py
random_regex/version.py
random_regex.egg-info/PKG-INFO
random_regex.egg-info/SOURCES.txt
random_regex.egg-info/dependency_links.txt
random_regex.egg-info/requires.txt
random_regex.egg-info/top_level.txt
random_regex/generator/__init__.py
random_regex/generator/generator.py
random_regex/generator/random_pattern.py