Metadata-Version: 2.1
Name: random-regex
Version: 1.0.0
Summary: Generate Random Regex
Home-page: https://github.com/jeffrey82221/regex_generator
Author: jeffreylin
Author-email: jeffrey82221@gmail.com
License: UNKNOWN
Platform: UNKNOWN
Classifier: Programming Language :: Python :: 3
Classifier: License :: OSI Approved :: MIT License
Classifier: Operating System :: OS Independent
Requires-Python: >=3.8, !=3.11.*
License-File: LICENSE
